{
  "hash": "076e4b3f252e6cb4e8c85b30c1910dc7",
  "result": {
    "engine": "knitr",
    "markdown": "---\ntitle: \"Day 5\"\ntitle-slide-attributes:\n  data-background-image: images/lake.jpg\n  data-background-size: contain\n  data-background-opacity: \"0.5\"\nsubtitle: \"Math 216: Statistical Thinking\"\nauthor: \"Bastola\"\nformat:\n  revealjs:\n    html-math-method: mathjax\n    mathjax-url: \"https://cdnjs.cloudflare.com/ajax/libs/mathjax/3.2.2/MathJax.js\" \n    theme: [default, scss/main.scss]\n    slide-number: true\n    preview-links: auto\n    history: true\n    chalkboard: \n      src: drawings.json\n    transition: slide\n    background-transition: fade    \n    touch: false\n    controls: true\n---\n\n\n\n## Introduction to Probability\n\n::: cle6\n::: font60\n\n- **Experiment**: Any act of observation with uncertain outcomes (e.g., tossing a coin).\n- **Observation**: The result of an experiment (e.g., heads or tails).\n- **Probability**: A measure of how likely an event is to occur, often thought of as \"chance\" or \"likelihood.\"\n  - Example: The chance of rain tomorrow, the likelihood of rolling a 6 on a die.\n\n\n### Mathematical Representation {.name}\n\n- Let $E$ represent an experiment.\n- An outcome of $E$ is an element of the sample space $S$.\n- Probability of an event $A$ is denoted by $P(A)$.\n\n:::\n:::\n\n\n## Key Definitions\n\n::: cle15\n::: font60\n\n### Sample Point {.name}\n\n- **Definition**: The most basic outcome of an experiment.\n- **Example**: In a coin toss, each toss that results in H (Head) or T (Tail).\n\n### Sample Space {.name}\n\n- **Definition**: Collection of all possible outcomes (sample points) of an experiment.\n- **Example**: In a coin toss, the sample space is $S = \\{H, T\\}$.\n\n### Event {.name}\n\n- **Definition**: A collection of sample points.\n- **Example**: Rolling an even number on a die.\n\n:::\n:::\n\n\n\n## Visualizing Probability\n\n::: cle6\n::: font70\n\n### Venn Diagram {.name}\n\n- **Sample Space (S)**: Represented as a closed figure in the diagram.\n- **Sample Points**: Each possible outcome shown as a solid dot within the figure.\n- **Example: Coin Toss**\n  - **Venn Diagram**: Circle labeled S containing two points labeled H (Head) and T (Tail).\n  - **Representation**: Helps visualize all possible outcomes in a single view.\n\n:::\n:::\n\n## Tree Diagram\n\n- **Example**: Tree diagram of a coin toss.\n\n![Tree diagram of a coin toss](images/coin_tree.png)\n\n\n\n\n## Experiments and Sample Spaces\n\n::: cle15\n::: font50\n\n**Experiment: Tossing a Coin**\n- **Sample Space (S)**: \n  $$S = \\{H, T\\}$$\n\n**Experiment: Rolling a Die**\n- **Sample Space (S)**: \n  $$S = \\{1, 2, 3, 4, 5, 6\\}$$\n\n**Experiment: Tossing Two Coins**\n- **Sample Space (S)**: \n  $$S = \\{HH, HT, TH, TT\\}$$\n\n:::\n:::\n\n## Probability Rules and Calculations\n\n::: cle14\n::: font60\n\n### Probability of a Sample Point {.name}\n\n- A number between 0 and 1 indicating the likelihood of the outcome.\n\n### Rules of Probability {.name}\n\n1. **Range of Probabilities**:\n   - Each probability $p_i$ must satisfy:\n     $$0 \\leq p_i \\leq 1$$\n2. **Sum of Probabilities**:\n   - The total probability across all sample points must sum to 1:\n     $$\\sum_{\\text{all } i} p_i = 1$$\n\n:::\n:::\n\n## Steps for Calculating Event Probabilities\n\n::: cle14\n::: font70\n\n1. **Define the Experiment**: Describe the observation process.\n2. **List Sample Points**: Identify possible outcomes.\n3. **Assign Probabilities**: Allocate probability to each sample point.\n4. **Identify Event's Sample Points**: Determine which sample points are part of the event.\n5. **Calculate Event Probability**: Sum the probabilities of the event's sample points.\n\n:::\n:::\n\n\n## Probability in a Dice Game\n\n::: cle13\n::: font50\n\n::: row\n::: left\n\n- **Experiment**: Tossing a fair die.\n- **Winning Condition**: If the up face is an even number (2, 4, 6), you win $1.\n- **Losing Condition**: If the up face is odd (1, 3, 5), you lose $1.\n\nSample Space and Probabilities \n\n- **Sample Space (S)**:\n  $$S = \\{1, 2, 3, 4, 5, 6\\}$$\n- **Uniform Probabilities**:\n  $$p_1 = p_2 = p_3 = \\cdots = p_6 = \\frac{1}{6}$$\n\n:::\n\n::: right\n\n::: name\nCalculation of Winning Probability \n:::\n\n- **Event of Winning**:\n  $$\\text{Winning} = \\{2, 4, 6\\}$$\n- **Probability of Winning**:\n  $$\\text{Prob of Winning} = p_2 + p_4 + p_6 = \\frac{1}{6} + \\frac{1}{6} + \\frac{1}{6} = \\frac{3}{6} = \\frac{1}{2}$$\n\n:::\n:::\n:::\n:::\n\n\n## Compound Events\n\n::: cle8\n::: font70\n\n### Unions\n- **Definition**: Union of two events $A$ and $B$ ($A \\cup B$)\n- **Occurs If**: Either event $A$, event $B$, or both happen.\n- **Composition**: Includes all sample points in $A$, $B$, or both.\n  $$A \\cup B = \\{x : x \\in A \\text{ or } x \\in B\\}$$\n\n### Intersections\n- **Definition**: Intersection of two events $A$ and $B$ ($A \\cap B$)\n- **Occurs If**: Both event $A$ and event $B$ happen.\n- **Composition**: Includes all sample points that are in both $A$ and $B$.\n  $$A \\cap B = \\{x : x \\in A \\text{ and } x \\in B\\}$$\n\n:::\n:::\n\n\n## Example: Calculating Unions and Intersections in a Die-Toss\n\n::: font60\n::: cle10\n\n::: row\n::: left\n\n- **Event A**: Toss an even number.\n  $$A = \\{2, 4, 6\\}$$\n- **Event B**: Toss a number less than or equal to 3.\n  $$B = \\{1, 2, 3\\}$$\n- **Sample Space (S)**:\n  $$S = \\{1, 2, 3, 4, 5, 6\\}$$\n\n:::\n\n::: right\n\n- **Union ($A \\cup B$)**:\n  $$A \\cup B = \\{1, 2, 3, 4, 6\\}$$\n- **Intersection ($A \\cap B$)**:\n  $$A \\cap B = \\{2\\}$$\n- **Probability of Union ($P(A \\cup B)$)**:\n  $$P(A \\cup B) = \\frac{5}{6}$$\n- **Probability of Intersection ($P(A \\cap B)$)**:\n  $$P(A \\cap B) = \\frac{1}{6}$$\n\n:::\n:::\n:::\n:::",
    "supporting": [],
    "filters": [
      "rmarkdown/pagebreak.lua"
    ],
    "includes": {
      "include-after-body": [
        "\n<script>\n  // htmlwidgets need to know to resize themselves when slides are shown/hidden.\n  // Fire the \"slideenter\" event (handled by htmlwidgets.js) when the current\n  // slide changes (different for each slide format).\n  (function () {\n    // dispatch for htmlwidgets\n    function fireSlideEnter() {\n      const event = window.document.createEvent(\"Event\");\n      event.initEvent(\"slideenter\", true, true);\n      window.document.dispatchEvent(event);\n    }\n\n    function fireSlideChanged(previousSlide, currentSlide) {\n      fireSlideEnter();\n\n      // dispatch for shiny\n      if (window.jQuery) {\n        if (previousSlide) {\n          window.jQuery(previousSlide).trigger(\"hidden\");\n        }\n        if (currentSlide) {\n          window.jQuery(currentSlide).trigger(\"shown\");\n        }\n      }\n    }\n\n    // hookup for slidy\n    if (window.w3c_slidy) {\n      window.w3c_slidy.add_observer(function (slide_num) {\n        // slide_num starts at position 1\n        fireSlideChanged(null, w3c_slidy.slides[slide_num - 1]);\n      });\n    }\n\n  })();\n</script>\n\n"
      ]
    },
    "engineDependencies": {},
    "preserve": {},
    "postProcess": true
  }
}